mongodb_database_automate/__init__.py
mongodb_database_automate/mongo_crud.py
mongodb_database_automate-0.0.7.dist-info/METADATA
mongodb_database_automate-0.0.7.dist-info/WHEEL
mongodb_database_automate-0.0.7.dist-info/top_level.txt
mongodb_database_automate-0.0.7.dist-info/RECORD
